py_cc_ohlcv/__init__.py
py_cc_ohlcv/exchange_functions.py
py_cc_ohlcv/exchange_metadata.py
py_cc_ohlcv/exchanges.py
py_cc_ohlcv/scraper.py
py_cc_ohlcv-0.1.1.dist-info/LICENSE
py_cc_ohlcv-0.1.1.dist-info/METADATA
py_cc_ohlcv-0.1.1.dist-info/WHEEL
py_cc_ohlcv-0.1.1.dist-info/top_level.txt
py_cc_ohlcv-0.1.1.dist-info/RECORD
