Metadata-Version: 2.1
Name: py-cc-ohlcv
Version: 0.1.1
Home-page: https://github.com/gmax0/Cryptocurrency-OHLCV-Scraper
Author: Max Gao
Author-email: gaamox@tutanota.com
License: MIT
Keywords: ohlcv,cryptocurrency,historical,market,data
License-File: LICENSE
Requires-Dist: pandas
Requires-Dist: requests
